insilicodna/__init__.py
insilicodna/application.py
insilicodna/cli.py
insilicodna/core.py
insilicodna/reference_genome.py
insilicodna-0.0.3.dist-info/LICENSE
insilicodna-0.0.3.dist-info/METADATA
insilicodna-0.0.3.dist-info/WHEEL
insilicodna-0.0.3.dist-info/entry_points.txt
insilicodna-0.0.3.dist-info/top_level.txt
insilicodna-0.0.3.dist-info/RECORD
