Metadata-Version: 2.1
Name: insilicodna
Version: 0.0.3
Summary: Generate synthetic molecular data
Home-page: https://github.com/keegankelsey/in-silico-dna
Author: Keegan Kelsey
Author-email: keegankelsey@gmail.com.com
License: UNKNOWN
Platform: UNKNOWN
Classifier: Development Status :: 1 - Planning
Classifier: Programming Language :: Python :: 3
Classifier: License :: OSI Approved :: MIT License
Classifier: Operating System :: OS Independent
Requires-Python: >=3.7
License-File: LICENSE
Requires-Dist: click
Provides-Extra: test
Requires-Dist: pytest ; extra == 'test'
